README.rst
setup.cfg
setup.py
interactive/__init__.py
interactive/plugin.py
interactive/shell.py
pytest_interactive.egg-info/PKG-INFO
pytest_interactive.egg-info/SOURCES.txt
pytest_interactive.egg-info/dependency_links.txt
pytest_interactive.egg-info/entry_points.txt
pytest_interactive.egg-info/not-zip-safe
pytest_interactive.egg-info/requires.txt
pytest_interactive.egg-info/top_level.txt