Metadata-Version: 1.1
Name: pytest-interactive
Version: 0.1.3
Summary: A pytest plugin for console based interactive test selection just after the collection phase
Home-page: https://github.com/tgoodlet/pytest-interactive
Author: Tyler Goodlet
Author-email: tgoodlet@gmail.com
License: MIT
Download-URL: https://github.com/tgoodlet/pytest-interactive/tarball/0.1
Platform: linux
Classifier: Development Status :: 3 - Alpha
Classifier: Intended Audience :: Developers
Classifier: License :: OSI Approved :: MIT License
Classifier: Operating System :: POSIX
Classifier: Operating System :: Microsoft :: Windows
Classifier: Operating System :: MacOS :: MacOS X
Classifier: Topic :: Software Development :: Testing
Classifier: Programming Language :: Python :: 2.7
Classifier: Programming Language :: Python :: 3
Classifier: Environment :: Console
